kmake/__init__.py
kmake/main.py
kmake-0.0.1.dist-info/LICENSE
kmake-0.0.1.dist-info/METADATA
kmake-0.0.1.dist-info/WHEEL
kmake-0.0.1.dist-info/entry_points.txt
kmake-0.0.1.dist-info/RECORD
